fuego/__init__.py
fuego/run_on_spaces.py
fuego/runtime.py
fuego-0.0.8.dist-info/LICENSE
fuego-0.0.8.dist-info/METADATA
fuego-0.0.8.dist-info/WHEEL
fuego-0.0.8.dist-info/entry_points.txt
fuego-0.0.8.dist-info/top_level.txt
fuego-0.0.8.dist-info/RECORD
