Metadata-Version: 2.1
Name: fuego
Version: 0.0.8
Summary: Fuego
Home-page: https://github.com/huggingface/fuego
Author: Nathan Raw
Author-email: nate@huggingface.com
License: Apache
License-File: LICENSE
Requires-Dist: fire
Requires-Dist: huggingface-hub (>=0.12.0)
Requires-Dist: GitPython
